{
	"configurations" : 
	[
		{
			"directories" : 
			[
				{
					"build" : ".",
					"jsonFile" : "directory-.-Debug-f5ebdc15457944623624.json",
					"minimumCMakeVersion" : 
					{
						"string" : "3.15"
					},
					"projectIndex" : 0,
					"source" : ".",
					"targetIndexes" : 
					[
						0
					]
				}
			],
			"name" : "Debug",
			"projects" : 
			[
				{
					"directoryIndexes" : 
					[
						0
					],
					"name" : "helloCFD",
					"targetIndexes" : 
					[
						0
					]
				}
			],
			"targets" : 
			[
				{
					"directoryIndex" : 0,
					"id" : "helloCFD::@6890427a1f51a3e7e1df",
					"jsonFile" : "target-helloCFD-Debug-6967efe260bedb29494c.json",
					"name" : "helloCFD",
					"projectIndex" : 0
				}
			]
		}
	],
	"kind" : "codemodel",
	"paths" : 
	{
		"build" : "/mnt/d/ArchLinux/CongFD/build",
		"source" : "/mnt/d/ArchLinux/CongFD"
	},
	"version" : 
	{
		"major" : 2,
		"minor" : 7
	}
}
